<annotation>
	<folder>train</folder>
	<filename>003_1_0094.png</filename>
	<path>C:\tensorflow\models\research\object_detection\images\train\003_1_0094.png</path>
	<source>
		<database>Unknown</database>
	</source>
	<size>
		<width>83</width>
		<height>80</height>
		<depth>3</depth>
	</size>
	<segmented>0</segmented>
	<object>
		<name>40</name>
		<pose>Unspecified</pose>
		<truncated>0</truncated>
		<difficult>0</difficult>
		<bndbox>
			<xmin>14</xmin>
			<ymin>9</ymin>
			<xmax>73</xmax>
			<ymax>66</ymax>
		</bndbox>
	</object>
</annotation>
